spindle/__init__.py
spindle_mcp-1.0.2.dist-info/licenses/LICENSE
spindle_mcp-1.0.2.dist-info/METADATA
spindle_mcp-1.0.2.dist-info/WHEEL
spindle_mcp-1.0.2.dist-info/entry_points.txt
spindle_mcp-1.0.2.dist-info/top_level.txt
spindle_mcp-1.0.2.dist-info/RECORD
