Metadata-Version: 2.4
Name: spindle-mcp
Version: 1.0.2
Summary: MCP server for Claude Code to Claude Code delegation
License-Expression: MIT
Project-URL: Homepage, https://github.com/smythp/spindle
Project-URL: Repository, https://github.com/smythp/spindle
Project-URL: Issues, https://github.com/smythp/spindle/issues
Keywords: mcp,claude,claude-code,agent,delegation,ai
Classifier: Development Status :: 4 - Beta
Classifier: Environment :: Console
Classifier: Intended Audience :: Developers
Classifier: Operating System :: OS Independent
Classifier: Programming Language :: Python :: 3
Classifier: Programming Language :: Python :: 3.10
Classifier: Programming Language :: Python :: 3.11
Classifier: Programming Language :: Python :: 3.12
Classifier: Topic :: Software Development :: Libraries :: Python Modules
Requires-Python: >=3.10
License-File: LICENSE
Requires-Dist: fastmcp>=2.0.0
Requires-Dist: uvicorn>=0.30.0
Provides-Extra: dev
Requires-Dist: pytest>=7.0; extra == "dev"
Requires-Dist: pytest-asyncio>=0.21; extra == "dev"
Requires-Dist: black>=24.0; extra == "dev"
Requires-Dist: ruff>=0.1.0; extra == "dev"
Dynamic: license-file
